gpx_scraper/LICENSE
gpx_scraper/README.md
gpx_scraper/__init__.py
gpx_scraper/__main__.py
gpx_scraper/scraper.py
gpx_scraper-1.0.0b0.dist-info/LICENSE
gpx_scraper-1.0.0b0.dist-info/METADATA
gpx_scraper-1.0.0b0.dist-info/WHEEL
gpx_scraper-1.0.0b0.dist-info/entry_points.txt
gpx_scraper-1.0.0b0.dist-info/RECORD
